CB2325NumericaG07/__init__.py
CB2325NumericaG07/aproximacao.py
CB2325NumericaG07/erros.py
CB2325NumericaG07/integracao.py
CB2325NumericaG07/interpolacao.py
CB2325NumericaG07/raizes.py
cb2325numericag07-1.0.0.dist-info/licenses/LICENSE
cb2325numericag07-1.0.0.dist-info/METADATA
cb2325numericag07-1.0.0.dist-info/WHEEL
cb2325numericag07-1.0.0.dist-info/top_level.txt
cb2325numericag07-1.0.0.dist-info/RECORD
