Metadata-Version: 2.4
Name: CB2325NumericaG07
Version: 1.0.0
Summary: 1ª Versão Final da biblioteca numérica básica para o curso de programação 2.
Author: Alunos do grupo 07
Project-URL: Repository, https://github.com/Mateus-Band/CB2325NumericaG07.git
Classifier: Programming Language :: Python :: 3
Classifier: Operating System :: OS Independent
Classifier: License :: OSI Approved :: MIT License
Requires-Python: >=3.8
License-File: LICENSE
Requires-Dist: matplotlib
Requires-Dist: pytest
Requires-Dist: numpy
Requires-Dist: sympy
Dynamic: license-file
